odoo10_addon_crm_rma_location-10.0.1.0.0-py2.7-nspkg.pth
odoo/addons/crm_rma_location/README.rst
odoo/addons/crm_rma_location/__init__.py
odoo/addons/crm_rma_location/__manifest__.py
odoo/addons/crm_rma_location/i18n/crm_rma_location_rma.pot
odoo/addons/crm_rma_location/i18n/de.po
odoo/addons/crm_rma_location/i18n/es.po
odoo/addons/crm_rma_location/i18n/es_MX.po
odoo/addons/crm_rma_location/i18n/es_PA.po
odoo/addons/crm_rma_location/i18n/es_VE.po
odoo/addons/crm_rma_location/i18n/fr.po
odoo/addons/crm_rma_location/i18n/pt_BR.po
odoo/addons/crm_rma_location/i18n/sl.po
odoo/addons/crm_rma_location/models/__init__.py
odoo/addons/crm_rma_location/models/stock_warehouse.py
odoo/addons/crm_rma_location/tests/__init__.py
odoo/addons/crm_rma_location/tests/test_location_rma.py
odoo/addons/crm_rma_location/views/stock_warehouse.xml
odoo10_addon_crm_rma_location-10.0.1.0.0.dist-info/DESCRIPTION.rst
odoo10_addon_crm_rma_location-10.0.1.0.0.dist-info/METADATA
odoo10_addon_crm_rma_location-10.0.1.0.0.dist-info/RECORD
odoo10_addon_crm_rma_location-10.0.1.0.0.dist-info/WHEEL
odoo10_addon_crm_rma_location-10.0.1.0.0.dist-info/metadata.json
odoo10_addon_crm_rma_location-10.0.1.0.0.dist-info/namespace_packages.txt
odoo10_addon_crm_rma_location-10.0.1.0.0.dist-info/top_level.txt
